MANIFEST.in
README
setup.py
menuproxy/__init__.py
menuproxy/importpath.py
menuproxy/points.py
menuproxy/proxies.py
menuproxy/utils.py
menuproxy/redsolution_setup/__init__.py
menuproxy/redsolution_setup/make.py
menuproxy/redsolution_setup/templates/menuproxy/redsolutioncms/base_menuproxy.html
menuproxy/redsolution_setup/templates/menuproxy/redsolutioncms/settings.pyt
menuproxy/templates/menuproxy/auto_menu.html
menuproxy/templates/menuproxy/breadcrumbs.html
menuproxy/templates/menuproxy/full_menu.html
menuproxy/templates/menuproxy/main_menu.html
menuproxy/templatetags/__init__.py
menuproxy/templatetags/menuproxy_tags.py
redsolutioncms.django_menu_proxy.egg-info/PKG-INFO
redsolutioncms.django_menu_proxy.egg-info/SOURCES.txt
redsolutioncms.django_menu_proxy.egg-info/dependency_links.txt
redsolutioncms.django_menu_proxy.egg-info/entry_points.txt
redsolutioncms.django_menu_proxy.egg-info/not-zip-safe
redsolutioncms.django_menu_proxy.egg-info/top_level.txt