Metadata-Version: 1.1
Name: redsolutioncms.django-menu-proxy
Version: 0.1.2
Summary: MenuProxy allows you to build dynamic menu on site using different models.
Home-page: http://packages.python.org/django-menu-proxy
Author: Alexander Ivanov
Author-email: alexander.ivanov@redsolution.ru
License: GPLv3
Keywords: django menu
Platform: UNKNOWN
Classifier: Development Status :: 3 - Alpha
Classifier: Intended Audience :: Developers
Classifier: License :: OSI Approved :: GNU General Public License (GPL)
Classifier: Framework :: Django
Classifier: Environment :: Web Environment
Classifier: Natural Language :: Russian
Classifier: Natural Language :: English
Classifier: Operating System :: OS Independent
Classifier: Programming Language :: Python
Classifier: Topic :: Internet :: WWW/HTTP :: Site Management
